LICENSE
MANIFEST.in
README.rst
setup.py
accelerator/__init__.py
accelerator/tests.py
accelerator/stores/__init__.py
accelerator/stores/inmemory.py
accelerator/stores/redis.py
wsgi_accelerator.egg-info/PKG-INFO
wsgi_accelerator.egg-info/SOURCES.txt
wsgi_accelerator.egg-info/dependency_links.txt
wsgi_accelerator.egg-info/not-zip-safe
wsgi_accelerator.egg-info/top_level.txt