Metadata-Version: 1.0
Name: wsgi-accelerator
Version: 0.1.0
Summary: Simple HTTP cache for WSGI apps with fine-grained invalidation
Home-page: https://github.com/cgbystrom/wsgi-accelerator
Author: Carl Byström
Author-email: cgbystrom@gmail.com
License: The MIT License
